{
	"animations": [
		{
			"offsets": [
				0,
				180
			],
			"loop": false,
			"fps": 24,
			"anim": "idle",
			"indices": [],
			"name": "Idle"
		},
		{
			"loop": false,
			"offsets": [
				0,
				167
			],
			"anim": "singLEFT",
			"fps": 24,
			"name": "Sing Left",
			"indices": []
		},
		{
			"loop": false,
			"offsets": [
				-46,
				126
			],
			"anim": "singDOWN",
			"fps": 24,
			"name": "Sing Down",
			"indices": []
		},
		{
			"loop": false,
			"offsets": [
				-16,
				227
			],
			"anim": "singUP",
			"fps": 24,
			"name": "Sing Up",
			"indices": []
		},
		{
			"loop": false,
			"offsets": [
				-6,
				212
			],
			"anim": "singRIGHT",
			"fps": 24,
			"name": "Sing Right",
			"indices": []
		}
	],
	"no_antialiasing": false,
	"image": "characters/WhittySprites",
	"position": [
		0,
		0
	],
	"healthicon": "whitty-n",
	"flip_x": false,
	"healthbar_colors": [
		32,
		32,
		32
	],
	"camera_position": [
		0,
		-290
	],
	"sing_duration": 6.1,
	"scale": 1
}